GameFrame/InputManager.py
GameFrame/Math.py
GameFrame/TileMap.py
GameFrame/__init__.py
GameFrame/shapesManager.py
gameframe-0.0.5.dist-info/LICENSE
gameframe-0.0.5.dist-info/METADATA
gameframe-0.0.5.dist-info/WHEEL
gameframe-0.0.5.dist-info/top_level.txt
gameframe-0.0.5.dist-info/RECORD
