Metadata-Version: 2.2
Name: gameFrame
Version: 0.0.5
Summary: A beta project.
Author-email: sfertig <sfertig007@gmail.com>
Classifier: Programming Language :: Python :: 3
Classifier: Operating System :: OS Independent
Requires-Python: >=3.8
License-File: LICENSE
